recruiter_notification_app/__init__.py
recruiter_notification_app/notification_app.py
recruiter_notification_app/recruiter_app_mailer.py
recruiter_notification_app/templates/home.html
recruiter_notification_app-0.0.13.dist-info/METADATA
recruiter_notification_app-0.0.13.dist-info/WHEEL
recruiter_notification_app-0.0.13.dist-info/top_level.txt
recruiter_notification_app-0.0.13.dist-info/RECORD
