Metadata-Version: 2.1
Name: recruiter-notification-app
Version: 0.0.13
Summary: This is hush hush recruiter notification app
Author-email: prabhu <prabhupad@somwwhe.com>
Classifier: Programming Language :: Python :: 3
Classifier: License :: OSI Approved :: MIT License
Classifier: Operating System :: OS Independent
Requires-Python: >=3.7
